procgen_mirror-0.10.7.dist-info/LICENSE
procgen_mirror-0.10.7.dist-info/METADATA
procgen_mirror-0.10.7.dist-info/top_level.txt
procgen_mirror-0.10.7.dist-info/RECORD
procgen_mirror-0.10.7.dist-info/WHEEL
procgen/interactive.py
procgen/state_test.py
procgen/__init__.py
procgen/env_test.py
procgen/env.py
procgen/version.txt
procgen/builder.py
procgen/gym_registration.py
procgen/data/assets/kenney/Ground/Snow/snowCliffAlt_left.png
procgen/data/assets/kenney/Ground/Snow/snowCenter_rounded.png
procgen/data/assets/kenney/Ground/Snow/snowCorner_left.png
procgen/data/assets/kenney/Ground/Snow/snowHalf.png
procgen/data/assets/kenney/Ground/Snow/snowCenter.png
procgen/data/assets/kenney/Ground/Snow/snowRight.png
procgen/data/assets/kenney/Ground/Snow/snowHill_right.png
procgen/data/assets/kenney/Ground/Snow/snowLeft.png
procgen/data/assets/kenney/Ground/Snow/snowCliffAlt_right.png
procgen/data/assets/kenney/Ground/Snow/snowCliff_left.png
procgen/data/assets/kenney/Ground/Snow/snowHalf_right.png
procgen/data/assets/kenney/Ground/Snow/snowCorner_right.png
procgen/data/assets/kenney/Ground/Snow/snowHalf_mid.png
procgen/data/assets/kenney/Ground/Snow/snow.png
procgen/data/assets/kenney/Ground/Snow/snowHill_left.png
procgen/data/assets/kenney/Ground/Snow/snowMid.png
procgen/data/assets/kenney/Ground/Snow/snowCliff_right.png
procgen/data/assets/kenney/Ground/Snow/snowHalf_left.png
procgen/data/assets/kenney/Ground/Planet/planetCorner_left.png
procgen/data/assets/kenney/Ground/Planet/planetCorner_right.png
procgen/data/assets/kenney/Ground/Planet/planet.png
procgen/data/assets/kenney/Ground/Planet/planetCliff_left.png
procgen/data/assets/kenney/Ground/Planet/planetHalf.png
procgen/data/assets/kenney/Ground/Planet/planetLeft.png
procgen/data/assets/kenney/Ground/Planet/planetHalf_right.png
procgen/data/assets/kenney/Ground/Planet/planetHill_right.png
procgen/data/assets/kenney/Ground/Planet/planetHalf_mid.png
procgen/data/assets/kenney/Ground/Planet/planetCliffAlt_left.png
procgen/data/assets/kenney/Ground/Planet/planetCenter_rounded.png
procgen/data/assets/kenney/Ground/Planet/planetCliffAlt_right.png
